odoo/addons/fetchmail_notify_error_to_sender/README.rst
odoo/addons/fetchmail_notify_error_to_sender/__init__.py
odoo/addons/fetchmail_notify_error_to_sender/__manifest__.py
odoo/addons/fetchmail_notify_error_to_sender/data/email_template_data.xml
odoo/addons/fetchmail_notify_error_to_sender/i18n/ca.po
odoo/addons/fetchmail_notify_error_to_sender/i18n/de.po
odoo/addons/fetchmail_notify_error_to_sender/i18n/es.po
odoo/addons/fetchmail_notify_error_to_sender/i18n/es_AR.po
odoo/addons/fetchmail_notify_error_to_sender/i18n/fetchmail_notify_error_to_sender.pot
odoo/addons/fetchmail_notify_error_to_sender/i18n/fr.po
odoo/addons/fetchmail_notify_error_to_sender/i18n/hr.po
odoo/addons/fetchmail_notify_error_to_sender/i18n/it.po
odoo/addons/fetchmail_notify_error_to_sender/i18n/pt_BR.po
odoo/addons/fetchmail_notify_error_to_sender/i18n/pt_PT.po
odoo/addons/fetchmail_notify_error_to_sender/i18n/sl.po
odoo/addons/fetchmail_notify_error_to_sender/i18n/tr.po
odoo/addons/fetchmail_notify_error_to_sender/i18n/zh_CN.po
odoo/addons/fetchmail_notify_error_to_sender/models/__init__.py
odoo/addons/fetchmail_notify_error_to_sender/models/fetchmail.py
odoo/addons/fetchmail_notify_error_to_sender/models/mail_thread.py
odoo/addons/fetchmail_notify_error_to_sender/readme/CONFIGURE.md
odoo/addons/fetchmail_notify_error_to_sender/readme/CONTRIBUTORS.md
odoo/addons/fetchmail_notify_error_to_sender/readme/DESCRIPTION.md
odoo/addons/fetchmail_notify_error_to_sender/static/description/icon.png
odoo/addons/fetchmail_notify_error_to_sender/static/description/index.html
odoo/addons/fetchmail_notify_error_to_sender/tests/__init__.py
odoo/addons/fetchmail_notify_error_to_sender/tests/test_fetchmail_notify_error_to_sender.py
odoo/addons/fetchmail_notify_error_to_sender/views/fetchmail_view.xml
odoo_addon_fetchmail_notify_error_to_sender-18.0.1.0.0.4.dist-info/METADATA
odoo_addon_fetchmail_notify_error_to_sender-18.0.1.0.0.4.dist-info/WHEEL
odoo_addon_fetchmail_notify_error_to_sender-18.0.1.0.0.4.dist-info/top_level.txt
odoo_addon_fetchmail_notify_error_to_sender-18.0.1.0.0.4.dist-info/RECORD
