Metadata-Version: 2.1
Name: odoo-addon-fetchmail_notify_error_to_sender
Version: 18.0.1.0.0.4
Requires-Python: >=3.10
Requires-Dist: odoo==18.0.*
Summary: If fetching mails gives error, send an email to sender
Home-page: https://github.com/OCA/server-tools
License: AGPL-3
Author: Agile Business Group,ForgeFlow,Odoo Community Association (OCA)
Author-email: support@odoo-community.org
Classifier: Programming Language :: Python
Classifier: Framework :: Odoo
Classifier: Framework :: Odoo :: 18.0
Classifier: License :: OSI Approved :: GNU Affero General Public License v3
